README.md
setup.py
analisischip/__init__.py
analisischip/__main__.py
analisischip/config.py
analisischip/seq.py
analisischip.egg-info/PKG-INFO
analisischip.egg-info/SOURCES.txt
analisischip.egg-info/dependency_links.txt
analisischip.egg-info/requires.txt
analisischip.egg-info/top_level.txt