Metadata-Version: 2.1
Name: analisischip
Version: 0.0.1
Summary: Herramientas para análisis de secuencias en resultados de ChIP-seq.
Home-page: https://github.com/EmilioKolo/analisissecuenciaschip
Author: Emilio Kolomenski
Author-email: ekolomenski@gmail.com
License: MIT
Platform: UNKNOWN
Classifier: Development Status :: 3 - Alpha
Classifier: Intended Audience :: Science/Research
Classifier: Topic :: Scientific/Engineering :: Bio-Informatics
Classifier: License :: OSI Approved :: MIT License
Classifier: Programming Language :: Python :: 3
